<?xml version="1.0" encoding="UTF-8"?>
<!DOCTYPE root>
<study>
  <patient>
    <ID>09284_1</ID>
    <UniquePatientIdentification>0</UniquePatientIdentification>
    <FirstName>WP300_NAF</FirstName>
    <LastName>NB</LastName>
    <Sex>N/A</Sex>
    <BirthDay format="M/d/yyyy"></BirthDay>
    <Weight units="Kg">0</Weight>
    <Height units="cm">0</Height>
    <NeckSize units="cm">0</NeckSize>
    <EpworthScore>-1</EpworthScore>
    <HomePhone></HomePhone>
    <WorkPhone></WorkPhone>
    <MobilePhone></MobilePhone>
    <Pager></Pager>
    <Email></Email>
    <Street></Street>
    <City></City>
    <ZipCode></ZipCode>
    <State></State>
    <Country></Country>
    <HistoryDisease></HistoryDisease>
    <Medication></Medication>
    <Pacemaker>no</Pacemaker>
  </patient>
  <physician>
    <PhysicianFirstName>N/A</PhysicianFirstName>
    <PhysicianLastName>N/A</PhysicianLastName>
    <PhysicianFaxPhone></PhysicianFaxPhone>
    <PhysicianWorkPhone></PhysicianWorkPhone>
    <PhysicianMobilePhone></PhysicianMobilePhone>
    <PhysicianPager></PhysicianPager>
    <PhysicianEmail></PhysicianEmail>
    <PhysicianStreet></PhysicianStreet>
    <PhysicianCity></PhysicianCity>
    <PhysicianZipCode></PhysicianZipCode>
    <PhysicianState></PhysicianState>
    <PhysicianCountry></PhysicianCountry>
    <PhysicianAffiliation></PhysicianAffiliation>
    <PhysicianLicense>N/A</PhysicianLicense>
  </physician>
  <Comments></Comments>
  <Coverage></Coverage>
  <PaymentCode></PaymentCode>
  <NumberOfNights>1</NumberOfNights>
  <BraceletStudy>no</BraceletStudy>
  <BraceletID></BraceletID>
  <StudyDate format="MM/DD/YYYY hh:mm:ss">01/10/2022 22:46:56</StudyDate>
  <HardwareVersion>4.2.1025</HardwareVersion>
  <SoftwareVersion>5.2.80.4</SoftwareVersion>
  <DeviceSN>308716</DeviceSN>
  <BraceletSN></BraceletSN>
  <analysis>
    <StudyStatus>0x28</StudyStatus>
    <Warnings></Warnings>
    <BraceletMessage></BraceletMessage>
    <StudyStartTime units="secs">82016</StudyStartTime>
    <StudyEndTime units="secs">23714</StudyEndTime>
    <TotalApneaSleepTime units="secs">23792</TotalApneaSleepTime>
    <TotalAH_CentralValidSleepTime units="secs">22390</TotalAH_CentralValidSleepTime>
    <TotalWakeTime units="secs">1997</TotalWakeTime>
    <TotalSleepTime units="secs">26101</TotalSleepTime>
    <TotalArousalSleepTime units="secs">26100</TotalArousalSleepTime>
    <NumberOfWakes>3</NumberOfWakes>
    <TotalREMTime units="secs">6360</TotalREMTime>
    <TotalDeepSleepTime units="secs">5401</TotalDeepSleepTime>
    <TotalLightSleepTime units="secs">14340</TotalLightSleepTime>
    <RDI>13.16</RDI>
    <AHI>11.35</AHI>
    <ODI>2.72</ODI>
    <AHICentral>0.00</AHICentral>
    <CSR_Percent>0.00</CSR_Percent>
    <REM_RDI>24.77</REM_RDI>
    <REM_AHI>20.52</REM_AHI>
    <REM_ODI>4.95</REM_ODI>
    <REM_AHICentral>0.00</REM_AHICentral>
    <NREM_RDI>10.01</NREM_RDI>
    <NREM_AHI>8.85</NREM_AHI>
    <NREM_ODI>2.12</NREM_ODI>
    <NREM_AHICentral>0.00</NREM_AHICentral>
    <TotalNumberOfApneas>87</TotalNumberOfApneas>
    <NumberOfMixedApneas>75</NumberOfMixedApneas>
    <NumberOfDesaturations>18</NumberOfDesaturations>
    <NumberOfCentralAH>0</NumberOfCentralAH>
    <REMLatency units="secs">7140.00</REMLatency>
    <SleepLatency units="secs">1170</SleepLatency>
    <SnoreThreshold units="db">45</SnoreThreshold>
    <MeanSnoreDB units="db">45</MeanSnoreDB>
    <SleepOverThreshold units="secs">9192</SleepOverThreshold>
    <SnoreAbove40 units="secs">15216</SnoreAbove40>
    <SnoreAbove50 units="secs">5892</SnoreAbove50>
    <SnoreAbove60 units="secs">588</SnoreAbove60>
    <SnoreAbove70 units="secs">0</SnoreAbove70>
    <SnoreAbove80 units="secs">0</SnoreAbove80>
    <SleepDuringProne units="secs">4710</SleepDuringProne>
    <SleepDuringSupine units="secs">17791</SleepDuringSupine>
    <SleepDuringLeft units="secs">3600</SleepDuringLeft>
    <SleepDuringRight units="secs">0</SleepDuringRight>
    <SleepDuringNonSupine units="secs">8310</SleepDuringNonSupine>
    <Prone_RDI>4.65</Prone_RDI>
    <Prone_AHI>4.65</Prone_AHI>
    <Prone_ODI>0.78</Prone_ODI>
    <Supine_RDI>17.96</Supine_RDI>
    <Supine_AHI>15.23</Supine_AHI>
    <Supine_ODI>3.64</Supine_ODI>
    <Left_RDI>2.18</Left_RDI>
    <Left_AHI>2.18</Left_AHI>
    <Left_ODI>1.09</Left_ODI>
    <Right_RDI>N/A</Right_RDI>
    <Right_AHI>N/A</Right_AHI>
    <Right_ODI>N/A</Right_ODI>
    <NonSupine_RDI>3.62</NonSupine_RDI>
    <NonSupine_AHI>3.62</NonSupine_AHI>
    <NonSupine_ODI>0.91</NonSupine_ODI>
    <MeanPRSleep>74</MeanPRSleep>
    <MinPRSleep>58</MinPRSleep>
    <MaxPRSleep>95</MaxPRSleep>
    <MeanSatValue>94</MeanSatValue>
    <MinSatValue>91</MinSatValue>
    <MaxSatValue>99</MaxSatValue>
    <MeanNadirDesaturations>93.22</MeanNadirDesaturations>
    <SatBelow90 units="secs">0</SatBelow90>
    <SatBelowEqual88 units="secs">0</SatBelowEqual88>
    <SatBelow88 units="secs">N/A</SatBelow88>
    <SatBelow85 units="secs">0</SatBelow85>
    <SatBelow80 units="secs">0</SatBelow80>
    <SatBelow70 units="secs">0</SatBelow70>
    <Desats2_3 units="secs">59</Desats2_3>
    <Desats4_9 units="secs">18</Desats4_9>
    <Desats10_9 units="secs">0</Desats10_9>
    <DesatsAbove20 units="secs">0</DesatsAbove20>
    <NumberOfMixedApneas_4_Percent>19</NumberOfMixedApneas_4_Percent>
    <AHI_4_Percent>2.87</AHI_4_Percent>
    <SnoreBPChart_Y_axis>Supine,Right,Left,Prone,Sit</SnoreBPChart_Y_axis>
    <SnoreDb_Y_axis>50,60,70,80</SnoreDb_Y_axis>
    <StagesChart_Y_axis>D Sleep,L Sleep,REM,Wake</StagesChart_Y_axis>
  </analysis>
</study>